{
  "address": "Xã Thanh Vân, Huyện Quản Bạ, Tỉnh Hà Giang",
  "ellapsedInMs": 7334,
  "estimatedCost": 0.0038206000000000004,
  "thought": "**Navigating the Reorganization of \"Xã Thanh Vân, Huyện Quản Bạ\"**\n\nOkay, so the user needs the new administrative unit for \"Xã Thanh Vân, Huyện Quản Bạ, Tỉnh Hà Giang.\" My first step is to confirm if there have been any province mergers. Checking \"60-NQ/TW,\" I see that \"Tỉnh Hà Giang\" is now part of \"Tỉnh Tuyên Quang.\" So, we're dealing with a province change.\n\nNext, I'll scour the resolutions, particularly focusing on those related to \"Tỉnh Tuyên Quang\" or the older \"Tỉnh Hà Giang.\" Looking at \"1684/NQ-UBTVQH15,\" I find some promising leads. Resolution 63 states that \"Xã Thanh Vân\" merges with \"Xã Nghĩa Thuận,\" resulting in a new entity named \"Xã Nghĩa Thuận.\" Resolution 64 mentions \"Xã Quản Bạ\" and its merger with two other wards to form the new \"Xã Quản Bạ.\"\n\nThis presents a slight ambiguity because the user's input specifies \"Huyện Quản Bạ\" (Quản Bạ District) and \"Xã Thanh Vân\" (Thanh Vân Ward/Commune). Resolution 63 clearly states \"Xã Thanh Vân\" changes to \"Xã Nghĩa Thuận\". Resolution 64 also changes Quản Bạ to Quản Bạ. Given the structure of the input address, it's clear that \"Thanh Vân\" is a ward *within* Quản Bạ District. Therefore, based on the resolutions, the new ward name for \"Xã Thanh Vân\" will be \"Xã Nghĩa Thuận\". I need to keep in mind that the new Quản Bạ is also a \"Xã.\"\n",
  "result": [
    {
      "citation": {
        "header": "60-NQ/TW: Các đơn vị hành chính cấp tỉnh mới sau sáp nhập, hợp nhất",
        "line": "1. Hợp nhất tỉnh Tuyên Quang và tỉnh Hà Giang, lấy tên là tỉnh Tuyên Quang"
      },
      "confidence": "high",
      "province_name": "Tỉnh Tuyên Quang",
      "ward_code": "00889",
      "ward_name": "Xã Nghĩa Thuận"
    }
  ]
}